{
    "id": "15w5ulq",
    "title": "Why are C-section deliveries rising in India? 🇮🇳",
    "url": "https://youtu.be/hrySl9ZaYz0",
    "selftext": "A food for thought?",
    "flair": "AskIndia",
    "score": 1,
    "num_comments": 0,
    "created_utc": 1692520332.0,
    "convurl": "https://external-preview.redd.it/qZLzytvh1g_CSabuAKvm0bERSn61QAw8DUPWyBVDb8s.jpg?auto=webp&s=73e21b1d6de9977026c78eb1b9f4ed953f6d31b8",
    "comments": [],
    "cleaned_text": "csection deliveries rising india food thought ",
    "cleaned_title": "csection deliveries rising india",
    "cleaned_selftext": "food thought",
    "cleaned_comments": "",
    "light_cleaned_title": "Why are C-section deliveries rising in India? 🇮🇳",
    "light_cleaned_selftext": "A food for thought?",
    "light_cleaned_comments": ""
}