{
    "id": "17icsyo",
    "title": "Wtf am I reading!?",
    "url": "https://www.indiatoday.in/cities/noida/story/noida-man-rapes-stray-dog-throws-from-3rd-floor-after-neighbour-sees-animal-cruelty-2454291-2023-10-27?utm_source=washare&utm_medium=socialicons&utm_campaign=shareurltracking",
    "selftext": "Noida man rapes stray dog, throws it from 3rd floor after being spotted; arrested.",
    "flair": "Crime",
    "score": 1,
    "num_comments": 0,
    "created_utc": 1698496337.0,
    "convurl": "https://external-preview.redd.it/7Sp3oTHDMKs_tgCaep5_xmaxs5iFUR2Q9vQ-fwbxUJo.jpg?auto=webp&s=793d1ebd30db5d786513538cc23ecc5f516ff36c",
    "comments": [],
    "cleaned_text": "wtf reading noida man rapes stray dog throws rd floor spotted arrested ",
    "cleaned_title": "wtf reading",
    "cleaned_selftext": "noida man rapes stray dog throws rd floor spotted arrested",
    "cleaned_comments": "",
    "light_cleaned_title": "Wtf am I reading!?",
    "light_cleaned_selftext": "Noida man rapes stray dog, throws it from 3rd floor after being spotted; arrested.",
    "light_cleaned_comments": ""
}