{
    "id": "159zqg8",
    "title": "What do you think about this BBC Article Pasted above about the Manipur Violence being a War on Drugs........",
    "url": "https://www.reddit.com/r/india/comments/159zqg8/what_do_you_think_about_this_bbc_article_pasted/",
    "selftext": "https://www.bbc.com/news/world-asia-india-66161535\n\nWhat do you think about this BBC Article Pasted above about the Manipur Violence being a War on Drugs........",
    "flair": "Politics",
    "score": 1,
    "num_comments": 1,
    "created_utc": 1690360028.0,
    "convurl": "https://external-preview.redd.it/F7e3tfYTsSp1cvQeYpBbEvdwmngQqs9EaUNBJNVV4ys.jpg?auto=webp&s=507d0ea8630239216d403f90ccbbf871810e2644",
    "comments": [],
    "cleaned_text": "think bbc article pasted manipur violence war drugs think bbc article pasted manipur violence war drugs ",
    "cleaned_title": "think bbc article pasted manipur violence war drugs",
    "cleaned_selftext": "think bbc article pasted manipur violence war drugs",
    "cleaned_comments": "",
    "light_cleaned_title": "What do you think about this BBC Article Pasted above about the Manipur Violence being a War on Drugs........",
    "light_cleaned_selftext": "What do you think about this BBC Article Pasted above about the Manipur Violence being a War on Drugs........",
    "light_cleaned_comments": ""
}