{
    "id": "17hpy19",
    "title": "Narayana Murthy: 'India's work productivity one of the lowest, youngsters should work 12 hours a day'",
    "url": "https://www.reddit.com/r/india/comments/17hpy19/narayana_murthy_indias_work_productivity_one_of/",
    "selftext": "Thoughts?\n\nhttps://www.businesstoday.in/latest/corporate/story/narayana-murthy-indias-work-productivity-one-of-the-lowest-youngsters-should-work-12-hours-a-day-403392-2023-10-26",
    "flair": "Policy/Economy",
    "score": 1,
    "num_comments": 1,
    "created_utc": 1698420043.0,
    "convurl": "https://external-preview.redd.it/9h15NUY0_-J_UHoN91fnED1_AQMtsXUNwYMYLORjHRk.jpg?auto=webp&s=718a7992f51e488c28ddafb3484876c8134909aa",
    "comments": [],
    "cleaned_text": "narayana murthy indias work productivity one lowest youngsters work hours day thoughts ",
    "cleaned_title": "narayana murthy indias work productivity one lowest youngsters work hours day",
    "cleaned_selftext": "thoughts",
    "cleaned_comments": "",
    "light_cleaned_title": "Narayana Murthy: 'India's work productivity one of the lowest, youngsters should work 12 hours a day'",
    "light_cleaned_selftext": "Thoughts?",
    "light_cleaned_comments": ""
}