{
    "id": "1c712vs",
    "title": "'Pranab Mukherjee, Chidambaram used to pressurise RBI to present rosier picture of growth,' claims ex-Governor Subbarao",
    "url": "https://www.businesstoday.in/latest/economy/story/pranab-mukherjee-chidambaram-used-to-pressurise-rbi-to-present-rosier-picture-of-growth-claims-ex-governor-subbarao-425610-2024-04-15",
    "selftext": "[deleted]",
    "flair": "Policy/Economy",
    "score": 1,
    "num_comments": 0,
    "created_utc": 1713440112.0,
    "convurl": "https://external-preview.redd.it/xNGvo1zVyREcUb8YEu58XpxWpsemCLDHJaLuvP8UGow.jpg?auto=webp&s=8bafd99aa50b6cf8e2b44ae2a781d412617daa13",
    "comments": [],
    "cleaned_text": "pranab mukherjee chidambaram used pressurise rbi present rosier picture growth claims exgovernor subbarao deleted ",
    "cleaned_title": "pranab mukherjee chidambaram used pressurise rbi present rosier picture growth claims exgovernor subbarao",
    "cleaned_selftext": "deleted",
    "cleaned_comments": "",
    "light_cleaned_title": "'Pranab Mukherjee, Chidambaram used to pressurise RBI to present rosier picture of growth,' claims ex-Governor Subbarao",
    "light_cleaned_selftext": "[deleted]",
    "light_cleaned_comments": ""
}