{
    "id": "1ai90f9",
    "title": "CBI searches 8 locations in West Bengal over CAPF recruitments based on forged domicile documents",
    "url": "https://www.deccanherald.com/india/west-bengal/cbi-searches-8-locations-in-west-bengal-over-capf-recruitments-based-on-forged-domicile-documents-2878281",
    "selftext": "Something is off in west Bengal.",
    "flair": "Crime",
    "score": 5,
    "num_comments": 0,
    "created_utc": 1707001818.0,
    "convurl": "https://external-preview.redd.it/Y-y_yPWHum7bbEicpYXheBOTZiBEXMEpxnM0PPQgEro.jpg?auto=webp&s=01302a88d284151d834e0313dd29a97551b593c3",
    "comments": [],
    "cleaned_text": "cbi searches locations west bengal capf recruitments based forged domicile documents something west bengal ",
    "cleaned_title": "cbi searches locations west bengal capf recruitments based forged domicile documents",
    "cleaned_selftext": "something west bengal",
    "cleaned_comments": "",
    "light_cleaned_title": "CBI searches 8 locations in West Bengal over CAPF recruitments based on forged domicile documents",
    "light_cleaned_selftext": "Something is off in west Bengal.",
    "light_cleaned_comments": ""
}