{
    "id": "16vh12p",
    "title": "Why everyone’s counting on the Census — and why a delay hurts",
    "url": "https://indianexpress.com/article/india/why-everyones-counting-on-the-census-and-why-a-delay-hurts-8961951/",
    "selftext": "Non paywalled link: https://12ft.io/proxy?q=https%3A%2F%2Findianexpress.com%2Farticle%2Findia%2Fwhy-everyones-counting-on-the-census-and-why-a-delay-hurts-8961951%2F+++",
    "flair": "Policy/Economy",
    "score": 1,
    "num_comments": 0,
    "created_utc": 1696006796.0,
    "convurl": "https://external-preview.redd.it/ssOsqq6nBOFYHlx5ciV6hkzw1Rjqzshwn5xOgGTaZoI.jpg?auto=webp&s=61ef3858ef816696aaaef1df5d760d5631928f91",
    "comments": [],
    "cleaned_text": "everyones counting census delay hurts non paywalled link ",
    "cleaned_title": "everyones counting census delay hurts",
    "cleaned_selftext": "non paywalled link",
    "cleaned_comments": "",
    "light_cleaned_title": "Why everyone’s counting on the Census — and why a delay hurts",
    "light_cleaned_selftext": "Non paywalled link:",
    "light_cleaned_comments": ""
}